authdog/__init__.py
authdog/__main__.py
authdog/__version__.py
authdog/login.py
authdog/login_test.py
authdog-0.1.0.dist-info/entry_points.txt
authdog-0.1.0.dist-info/WHEEL
authdog-0.1.0.dist-info/METADATA
authdog-0.1.0.dist-info/RECORD
