Metadata-Version: 2.1
Name: authdog
Version: 0.1.0
Summary: Authdog command line interface
Author: David Barrat
Author-email: david@barrat.io
Requires-Python: >=3.8,<4.0
Classifier: Programming Language :: Python :: 3
Classifier: Programming Language :: Python :: 3.8
Classifier: Programming Language :: Python :: 3.9
Requires-Dist: fire (>=0.4.0,<0.5.0)
